{
  "id": "3127236",
  "topic_id": "277",
  "title": "Pancreatic Cyst",
  "url": "https://acsearch.acr.org/docs/3127236/Narrative/",
  "body_regions": [
    "abdomen"
  ],
  "procedures": [
    {
      "name": "Pancreas cyst, <=2.5cm, incidental, initial evaluation",
      "score": 9,
      "rating": "Usually Appropriate"
    },
    {
      "name": "MRI abdomen without IV contrast with MRCP",
      "score": 5,
      "rating": "May Be Appropriate"
    },
    {
      "name": "CT abdomen with IV contrast multiphase",
      "score": 5,
      "rating": "May Be Appropriate"
    },
    {
      "name": "US abdomen endoscopic",
      "score": 2,
      "rating": "Usually Not Appropriate"
    },
    {
      "name": "CT abdomen without IV contrast",
      "score": 2,
      "rating": "Usually Not Appropriate"
    },
    {
      "name": "CT abdomen without and with IV contrast",
      "score": 2,
      "rating": "Usually Not Appropriate"
    },
    {
      "name": "Pancreas cyst, >2.5cm, incidental, no high risk features, initial evaluation",
      "score": 9,
      "rating": "Usually Appropriate"
    },
    {
      "name": "US abdomen endoscopic",
      "score": 5,
      "rating": "May Be Appropriate"
    },
    {
      "name": "MRI abdomen without IV contrast with MRCP",
      "score": 5,
      "rating": "May Be Appropriate"
    },
    {
      "name": "CT abdomen with IV contrast multiphase",
      "score": 5,
      "rating": "May Be Appropriate"
    },
    {
      "name": "CT abdomen without IV contrast",
      "score": 2,
      "rating": "Usually Not Appropriate"
    },
    {
      "name": "CT abdomen without and with IV contrast",
      "score": 2,
      "rating": "Usually Not Appropriate"
    },
    {
      "name": "Pancreas cyst, >2.5cm, incidental, high risk features, initial evaluation",
      "score": 9,
      "rating": "Usually Appropriate"
    },
    {
      "name": "MRI abdomen without and with IV contrast with MRCP",
      "score": 9,
      "rating": "Usually Appropriate"
    },
    {
      "name": "MRI abdomen without IV contrast with MRCP",
      "score": 5,
      "rating": "May Be Appropriate"
    },
    {
      "name": "CT abdomen with IV contrast multiphase",
      "score": 5,
      "rating": "May Be Appropriate"
    },
    {
      "name": "CT abdomen without IV contrast",
      "score": 2,
      "rating": "Usually Not Appropriate"
    },
    {
      "name": "CT abdomen without and with IV contrast",
      "score": 2,
      "rating": "Usually Not Appropriate"
    },
    {
      "name": "Pancreas duct dilation, >7mm, IPMN suspected, initial evaluation",
      "score": 9,
      "rating": "Usually Appropriate"
    },
    {
      "name": "MRI abdomen without and with IV contrast with MRCP",
      "score": 9,
      "rating": "Usually Appropriate"
    },
    {
      "name": "MRI abdomen without IV contrast with MRCP",
      "score": 9,
      "rating": "Usually Appropriate"
    },
    {
      "name": "CT abdomen with IV contrast multiphase",
      "score": 5,
      "rating": "May Be Appropriate"
    },
    {
      "name": "CT abdomen without IV contrast",
      "score": 2,
      "rating": "Usually Not Appropriate"
    },
    {
      "name": "CT abdomen without and with IV contrast",
      "score": 2,
      "rating": "Usually Not Appropriate"
    },
    {
      "name": "Pancreas cyst, follow-up imaging",
      "score": 9,
      "rating": "Usually Appropriate"
    },
    {
      "name": "MRI abdomen without IV contrast with MRCP",
      "score": 9,
      "rating": "Usually Appropriate"
    },
    {
      "name": "CT abdomen with IV contrast multiphase",
      "score": 9,
      "rating": "Usually Appropriate"
    },
    {
      "name": "US abdomen endoscopic",
      "score": 2,
      "rating": "Usually Not Appropriate"
    },
    {
      "name": "CT abdomen without IV contrast",
      "score": 2,
      "rating": "Usually Not Appropriate"
    },
    {
      "name": "CT abdomen without and with IV contrast",
      "score": 2,
      "rating": "Usually Not Appropriate"
    }
  ],
  "updated_at": "2026-01-28T21:09:35.247369+00:00"
}