{
  "id": "69371",
  "topic_id": "35",
  "title": "Pretreatment Detection, Surveillance, and Staging of Prostate Cancer",
  "url": "https://acsearch.acr.org/docs/69371/Narrative/",
  "body_regions": [
    "pelvis"
  ],
  "procedures": [
    {
      "name": "Prostate cancer suspected, no prior biopsy, initial diagnosis, initial imaging",
      "score": 9,
      "rating": "Usually Appropriate"
    },
    {
      "name": "TRUS-guided biopsy prostate",
      "score": 9,
      "rating": "Usually Appropriate"
    },
    {
      "name": "MRI pelvis without and with IV contrast",
      "score": 9,
      "rating": "Usually Appropriate"
    },
    {
      "name": "MRI pelvis without IV contrast",
      "score": 9,
      "rating": "Usually Appropriate"
    },
    {
      "name": "TRUS prostate",
      "score": 2,
      "rating": "Usually Not Appropriate"
    },
    {
      "name": "MRI abdomen and pelvis without and with IV contrast",
      "score": 2,
      "rating": "Usually Not Appropriate"
    },
    {
      "name": "MRI abdomen and pelvis without IV contrast",
      "score": 2,
      "rating": "Usually Not Appropriate"
    },
    {
      "name": "MRI whole body without and with IV contrast",
      "score": 2,
      "rating": "Usually Not Appropriate"
    },
    {
      "name": "MRI whole body without IV contrast",
      "score": 2,
      "rating": "Usually Not Appropriate"
    },
    {
      "name": "Bone scan whole body",
      "score": 2,
      "rating": "Usually Not Appropriate"
    },
    {
      "name": "Choline PET/CT skull base to mid-thigh",
      "score": 2,
      "rating": "Usually Not Appropriate"
    },
    {
      "name": "Choline PET/MRI  skull base to mid-thigh",
      "score": 2,
      "rating": "Usually Not Appropriate"
    },
    {
      "name": "CT abdomen and pelvis with IV contrast",
      "score": 2,
      "rating": "Usually Not Appropriate"
    },
    {
      "name": "CT abdomen and pelvis without IV contrast",
      "score": 2,
      "rating": "Usually Not Appropriate"
    },
    {
      "name": "FDG-PET/MRI skull base to mid-thigh",
      "score": 2,
      "rating": "Usually Not Appropriate"
    },
    {
      "name": "Fluciclovine PET/MRI skull base to mid-thigh",
      "score": 2,
      "rating": "Usually Not Appropriate"
    },
    {
      "name": "CT abdomen and pelvis without and with IV contrast",
      "score": 2,
      "rating": "Usually Not Appropriate"
    },
    {
      "name": "CT chest abdomen pelvis with IV contrast",
      "score": 2,
      "rating": "Usually Not Appropriate"
    },
    {
      "name": "CT chest abdomen pelvis without and with IV contrast",
      "score": 2,
      "rating": "Usually Not Appropriate"
    },
    {
      "name": "CT chest abdomen pelvis without IV contrast",
      "score": 2,
      "rating": "Usually Not Appropriate"
    },
    {
      "name": "FDG-PET/CT whole body",
      "score": 2,
      "rating": "Usually Not Appropriate"
    },
    {
      "name": "Fluciclovine PET/CT skull base to mid-thigh",
      "score": 2,
      "rating": "Usually Not Appropriate"
    },
    {
      "name": "Fluoride PET/CT whole body",
      "score": 2,
      "rating": "Usually Not Appropriate"
    },
    {
      "name": "PSMA PET/CT skull base to mid-thigh",
      "score": 2,
      "rating": "Usually Not Appropriate"
    },
    {
      "name": "Prostate cancer suspected, TRUS guided biopsy negative, initial diagnosis, next imaging study",
      "score": 9,
      "rating": "Usually Appropriate"
    },
    {
      "name": "TRUS-guided biopsy prostate",
      "score": 9,
      "rating": "Usually Appropriate"
    },
    {
      "name": "MRI pelvis without and with IV contrast",
      "score": 9,
      "rating": "Usually Appropriate"
    },
    {
      "name": "MRI pelvis without IV contrast",
      "score": 9,
      "rating": "Usually Appropriate"
    },
    {
      "name": "TRUS prostate",
      "score": 2,
      "rating": "Usually Not Appropriate"
    },
    {
      "name": "MRI abdomen and pelvis without and with IV contrast",
      "score": 2,
      "rating": "Usually Not Appropriate"
    },
    {
      "name": "MRI abdomen and pelvis without IV contrast",
      "score": 2,
      "rating": "Usually Not Appropriate"
    },
    {
      "name": "MRI whole body without and with IV contrast",
      "score": 2,
      "rating": "Usually Not Appropriate"
    },
    {
      "name": "MRI whole body without IV contrast",
      "score": 2,
      "rating": "Usually Not Appropriate"
    },
    {
      "name": "Bone scan whole body",
      "score": 2,
      "rating": "Usually Not Appropriate"
    },
    {
      "name": "Choline PET/CT skull base to mid-thigh",
      "score": 2,
      "rating": "Usually Not Appropriate"
    },
    {
      "name": "Choline PET/MRI  skull base to mid-thigh",
      "score": 2,
      "rating": "Usually Not Appropriate"
    },
    {
      "name": "CT abdomen and pelvis with IV contrast",
      "score": 2,
      "rating": "Usually Not Appropriate"
    },
    {
      "name": "CT abdomen and pelvis without IV contrast",
      "score": 2,
      "rating": "Usually Not Appropriate"
    },
    {
      "name": "FDG-PET/MRI skull base to mid-thigh",
      "score": 2,
      "rating": "Usually Not Appropriate"
    },
    {
      "name": "Fluciclovine PET/MRI skull base to mid-thigh",
      "score": 2,
      "rating": "Usually Not Appropriate"
    },
    {
      "name": "CT abdomen and pelvis without and with IV contrast",
      "score": 2,
      "rating": "Usually Not Appropriate"
    },
    {
      "name": "CT chest abdomen pelvis with IV contrast",
      "score": 2,
      "rating": "Usually Not Appropriate"
    },
    {
      "name": "CT chest abdomen pelvis without and with IV contrast",
      "score": 2,
      "rating": "Usually Not Appropriate"
    },
    {
      "name": "CT chest abdomen pelvis without IV contrast",
      "score": 2,
      "rating": "Usually Not Appropriate"
    },
    {
      "name": "FDG-PET/CT whole body",
      "score": 2,
      "rating": "Usually Not Appropriate"
    },
    {
      "name": "Fluciclovine PET/CT skull base to mid-thigh",
      "score": 2,
      "rating": "Usually Not Appropriate"
    },
    {
      "name": "Fluoride PET/CT whole body",
      "score": 2,
      "rating": "Usually Not Appropriate"
    },
    {
      "name": "PSMA PET/CT skull base to mid-thigh",
      "score": 2,
      "rating": "Usually Not Appropriate"
    },
    {
      "name": "Prostate cancer, low risk, active surveillance",
      "score": 9,
      "rating": "Usually Appropriate"
    },
    {
      "name": "TRUS-guided biopsy prostate",
      "score": 9,
      "rating": "Usually Appropriate"
    },
    {
      "name": "MRI pelvis without and with IV contrast",
      "score": 9,
      "rating": "Usually Appropriate"
    },
    {
      "name": "MRI pelvis without IV contrast",
      "score": 9,
      "rating": "Usually Appropriate"
    },
    {
      "name": "TRUS prostate",
      "score": 2,
      "rating": "Usually Not Appropriate"
    },
    {
      "name": "MRI abdomen and pelvis without and with IV contrast",
      "score": 2,
      "rating": "Usually Not Appropriate"
    },
    {
      "name": "MRI abdomen and pelvis without IV contrast",
      "score": 2,
      "rating": "Usually Not Appropriate"
    },
    {
      "name": "MRI whole body without and with IV contrast",
      "score": 2,
      "rating": "Usually Not Appropriate"
    },
    {
      "name": "MRI whole body without IV contrast",
      "score": 2,
      "rating": "Usually Not Appropriate"
    },
    {
      "name": "Bone scan whole body",
      "score": 2,
      "rating": "Usually Not Appropriate"
    },
    {
      "name": "Choline PET/CT skull base to mid-thigh",
      "score": 2,
      "rating": "Usually Not Appropriate"
    },
    {
      "name": "Choline PET/MRI  skull base to mid-thigh",
      "score": 2,
      "rating": "Usually Not Appropriate"
    },
    {
      "name": "CT abdomen and pelvis with IV contrast",
      "score": 2,
      "rating": "Usually Not Appropriate"
    },
    {
      "name": "CT abdomen and pelvis without IV contrast",
      "score": 2,
      "rating": "Usually Not Appropriate"
    },
    {
      "name": "FDG-PET/MRI skull base to mid-thigh",
      "score": 2,
      "rating": "Usually Not Appropriate"
    },
    {
      "name": "Fluciclovine PET/MRI skull base to mid-thigh",
      "score": 2,
      "rating": "Usually Not Appropriate"
    },
    {
      "name": "CT abdomen and pelvis without and with IV contrast",
      "score": 2,
      "rating": "Usually Not Appropriate"
    },
    {
      "name": "CT chest abdomen pelvis with IV contrast",
      "score": 2,
      "rating": "Usually Not Appropriate"
    },
    {
      "name": "CT chest abdomen pelvis without and with IV contrast",
      "score": 2,
      "rating": "Usually Not Appropriate"
    },
    {
      "name": "CT chest abdomen pelvis without IV contrast",
      "score": 2,
      "rating": "Usually Not Appropriate"
    },
    {
      "name": "FDG-PET/CT whole body",
      "score": 2,
      "rating": "Usually Not Appropriate"
    },
    {
      "name": "Fluciclovine PET/CT skull base to mid-thigh",
      "score": 2,
      "rating": "Usually Not Appropriate"
    },
    {
      "name": "Fluoride PET/CT whole body",
      "score": 2,
      "rating": "Usually Not Appropriate"
    },
    {
      "name": "PSMA PET/CT skull base to mid-thigh",
      "score": 2,
      "rating": "Usually Not Appropriate"
    },
    {
      "name": "Prostate cancer, intermediate risk, active surveillance",
      "score": 9,
      "rating": "Usually Appropriate"
    },
    {
      "name": "MRI abdomen and pelvis without and with IV contrast",
      "score": 9,
      "rating": "Usually Appropriate"
    },
    {
      "name": "MRI pelvis without and with IV contrast",
      "score": 9,
      "rating": "Usually Appropriate"
    },
    {
      "name": "CT abdomen and pelvis with IV contrast",
      "score": 9,
      "rating": "Usually Appropriate"
    },
    {
      "name": "CT chest abdomen pelvis with IV contrast",
      "score": 9,
      "rating": "Usually Appropriate"
    },
    {
      "name": "Fluciclovine PET/CT skull base to mid-thigh",
      "score": 9,
      "rating": "Usually Appropriate"
    },
    {
      "name": "PSMA PET/CT skull base to mid-thigh",
      "score": 9,
      "rating": "Usually Appropriate"
    },
    {
      "name": "TRUS-guided biopsy prostate",
      "score": 5,
      "rating": "May Be Appropriate"
    },
    {
      "name": "MRI abdomen and pelvis without IV contrast",
      "score": 5,
      "rating": "May Be Appropriate"
    },
    {
      "name": "MRI pelvis without IV contrast",
      "score": 5,
      "rating": "May Be Appropriate"
    },
    {
      "name": "MRI whole body without and with IV contrast",
      "score": 5,
      "rating": "May Be Appropriate"
    },
    {
      "name": "MRI whole body without IV contrast",
      "score": 5,
      "rating": "May Be Appropriate"
    },
    {
      "name": "Bone scan whole body",
      "score": 5,
      "rating": "May Be Appropriate"
    },
    {
      "name": "Choline PET/CT skull base to mid-thigh",
      "score": 5,
      "rating": "May Be Appropriate"
    },
    {
      "name": "Choline PET/MRI  skull base to mid-thigh",
      "score": 5,
      "rating": "May Be Appropriate"
    },
    {
      "name": "CT abdomen and pelvis without IV contrast",
      "score": 5,
      "rating": "May Be Appropriate"
    },
    {
      "name": "Fluciclovine PET/MRI skull base to mid-thigh",
      "score": 5,
      "rating": "May Be Appropriate"
    },
    {
      "name": "CT abdomen and pelvis without and with IV contrast",
      "score": 5,
      "rating": "May Be Appropriate"
    },
    {
      "name": "CT chest abdomen pelvis without IV contrast",
      "score": 5,
      "rating": "May Be Appropriate"
    },
    {
      "name": "Fluoride PET/CT whole body",
      "score": 5,
      "rating": "May Be Appropriate"
    },
    {
      "name": "TRUS prostate",
      "score": 2,
      "rating": "Usually Not Appropriate"
    },
    {
      "name": "FDG-PET/MRI skull base to mid-thigh",
      "score": 2,
      "rating": "Usually Not Appropriate"
    },
    {
      "name": "CT chest abdomen pelvis without and with IV contrast",
      "score": 2,
      "rating": "Usually Not Appropriate"
    },
    {
      "name": "FDG-PET/CT whole body",
      "score": 2,
      "rating": "Usually Not Appropriate"
    },
    {
      "name": "Prostate cancer, intermediate risk, staging",
      "score": 9,
      "rating": "Usually Appropriate"
    },
    {
      "name": "MRI abdomen and pelvis without and with IV contrast",
      "score": 9,
      "rating": "Usually Appropriate"
    },
    {
      "name": "MRI pelvis without and with IV contrast",
      "score": 9,
      "rating": "Usually Appropriate"
    },
    {
      "name": "CT abdomen and pelvis with IV contrast",
      "score": 9,
      "rating": "Usually Appropriate"
    },
    {
      "name": "CT chest abdomen pelvis with IV contrast",
      "score": 9,
      "rating": "Usually Appropriate"
    },
    {
      "name": "Fluciclovine PET/CT skull base to mid-thigh",
      "score": 9,
      "rating": "Usually Appropriate"
    },
    {
      "name": "PSMA PET/CT skull base to mid-thigh",
      "score": 9,
      "rating": "Usually Appropriate"
    },
    {
      "name": "TRUS-guided biopsy prostate",
      "score": 5,
      "rating": "May Be Appropriate"
    },
    {
      "name": "MRI abdomen and pelvis without IV contrast",
      "score": 5,
      "rating": "May Be Appropriate"
    },
    {
      "name": "MRI pelvis without IV contrast",
      "score": 5,
      "rating": "May Be Appropriate"
    },
    {
      "name": "MRI whole body without and with IV contrast",
      "score": 5,
      "rating": "May Be Appropriate"
    },
    {
      "name": "MRI whole body without IV contrast",
      "score": 5,
      "rating": "May Be Appropriate"
    },
    {
      "name": "Bone scan whole body",
      "score": 5,
      "rating": "May Be Appropriate"
    },
    {
      "name": "Choline PET/CT skull base to mid-thigh",
      "score": 5,
      "rating": "May Be Appropriate"
    },
    {
      "name": "Choline PET/MRI  skull base to mid-thigh",
      "score": 5,
      "rating": "May Be Appropriate"
    },
    {
      "name": "CT abdomen and pelvis without IV contrast",
      "score": 5,
      "rating": "May Be Appropriate"
    },
    {
      "name": "Fluciclovine PET/MRI skull base to mid-thigh",
      "score": 5,
      "rating": "May Be Appropriate"
    },
    {
      "name": "CT abdomen and pelvis without and with IV contrast",
      "score": 5,
      "rating": "May Be Appropriate"
    },
    {
      "name": "CT chest abdomen pelvis without IV contrast",
      "score": 5,
      "rating": "May Be Appropriate"
    },
    {
      "name": "Fluoride PET/CT whole body",
      "score": 5,
      "rating": "May Be Appropriate"
    },
    {
      "name": "TRUS prostate",
      "score": 2,
      "rating": "Usually Not Appropriate"
    },
    {
      "name": "FDG-PET/MRI skull base to mid-thigh",
      "score": 2,
      "rating": "Usually Not Appropriate"
    },
    {
      "name": "CT chest abdomen pelvis without and with IV contrast",
      "score": 2,
      "rating": "Usually Not Appropriate"
    },
    {
      "name": "FDG-PET/CT whole body",
      "score": 2,
      "rating": "Usually Not Appropriate"
    },
    {
      "name": "Prostate cancer, high risk, staging",
      "score": 9,
      "rating": "Usually Appropriate"
    },
    {
      "name": "MRI pelvis without and with IV contrast",
      "score": 9,
      "rating": "Usually Appropriate"
    },
    {
      "name": "Bone scan whole body",
      "score": 9,
      "rating": "Usually Appropriate"
    },
    {
      "name": "Choline PET/CT skull base to mid-thigh",
      "score": 9,
      "rating": "Usually Appropriate"
    },
    {
      "name": "Choline PET/MRI  skull base to mid-thigh",
      "score": 9,
      "rating": "Usually Appropriate"
    },
    {
      "name": "CT abdomen and pelvis with IV contrast",
      "score": 9,
      "rating": "Usually Appropriate"
    },
    {
      "name": "Fluciclovine PET/MRI skull base to mid-thigh",
      "score": 9,
      "rating": "Usually Appropriate"
    },
    {
      "name": "CT chest abdomen pelvis with IV contrast",
      "score": 9,
      "rating": "Usually Appropriate"
    },
    {
      "name": "Fluciclovine PET/CT skull base to mid-thigh",
      "score": 9,
      "rating": "Usually Appropriate"
    },
    {
      "name": "Fluoride PET/CT whole body",
      "score": 9,
      "rating": "Usually Appropriate"
    },
    {
      "name": "PSMA PET/CT skull base to mid-thigh",
      "score": 9,
      "rating": "Usually Appropriate"
    },
    {
      "name": "MRI abdomen and pelvis without IV contrast",
      "score": 5,
      "rating": "May Be Appropriate"
    },
    {
      "name": "MRI pelvis without IV contrast",
      "score": 5,
      "rating": "May Be Appropriate"
    },
    {
      "name": "MRI whole body without and with IV contrast",
      "score": 5,
      "rating": "May Be Appropriate"
    },
    {
      "name": "MRI whole body without IV contrast",
      "score": 5,
      "rating": "May Be Appropriate"
    },
    {
      "name": "CT abdomen and pelvis without IV contrast",
      "score": 5,
      "rating": "May Be Appropriate"
    },
    {
      "name": "CT abdomen and pelvis without and with IV contrast",
      "score": 5,
      "rating": "May Be Appropriate"
    },
    {
      "name": "CT chest abdomen pelvis without IV contrast",
      "score": 5,
      "rating": "May Be Appropriate"
    },
    {
      "name": "MRI-targeted biopsy prostate",
      "score": 2,
      "rating": "Usually Not Appropriate"
    },
    {
      "name": "TRUS prostate",
      "score": 2,
      "rating": "Usually Not Appropriate"
    },
    {
      "name": "TRUS-guided biopsy prostate",
      "score": 2,
      "rating": "Usually Not Appropriate"
    },
    {
      "name": "FDG-PET/MRI skull base to mid-thigh",
      "score": 2,
      "rating": "Usually Not Appropriate"
    },
    {
      "name": "CT chest abdomen pelvis without and with IV contrast",
      "score": 2,
      "rating": "Usually Not Appropriate"
    },
    {
      "name": "FDG-PET/CT whole body",
      "score": 2,
      "rating": "Usually Not Appropriate"
    }
  ],
  "updated_at": "2026-01-28T21:15:30.261998+00:00"
}